iqsuite/__init__.py
iqsuite/client.py
iqsuite/exceptions.py
iqsuite/models.py
iqsuite/utils.py
iqsuite-0.1.7.dist-info/LICENSE
iqsuite-0.1.7.dist-info/METADATA
iqsuite-0.1.7.dist-info/WHEEL
iqsuite-0.1.7.dist-info/top_level.txt
iqsuite-0.1.7.dist-info/RECORD
