Metadata-Version: 2.2
Name: iqsuite
Version: 0.1.7
Summary: Python SDK for IQSuite API
Home-page: https://github.com/iQSuite/platform-sdk-python
Author: iQ Suite
Author-email: support@iqsuite.ai
Classifier: Development Status :: 3 - Alpha
Classifier: Intended Audience :: Developers
Classifier: License :: OSI Approved :: MIT License
Classifier: Programming Language :: Python :: 3
Classifier: Programming Language :: Python :: 3.7
Classifier: Programming Language :: Python :: 3.8
Classifier: Programming Language :: Python :: 3.9
Requires-Python: >=3.7
License-File: LICENSE
Requires-Dist: requests>=2.25.0
Requires-Dist: pydantic>=2.0.0
Dynamic: author
Dynamic: author-email
Dynamic: classifier
Dynamic: description
Dynamic: description-content-type
Dynamic: home-page
Dynamic: requires-dist
Dynamic: requires-python
Dynamic: summary
